hexometry/__init__.py
hexometry/coordinates.py
hexometry/grids.py
hexometry-1.1.1.dist-info/LICENSE
hexometry-1.1.1.dist-info/WHEEL
hexometry-1.1.1.dist-info/METADATA
hexometry-1.1.1.dist-info/RECORD
