Metadata-Version: 2.3
Name: hexometry
Version: 1.1.1
Summary: **Hexometry**
Author-email: wlame <wlarne@gmail.com>
Requires-Python: >=3.11
Classifier: License :: OSI Approved :: MIT License
Project-URL: Home, https://github.com/wlame/hexometry
